ubicquia/__init__.py
ubicquia/base.py
ubicquia/base_models.py
ubicquia/client.py
ubicquia/light_control.py
ubicquia/light_control_models.py
ubicquia/nodes.py
ubicquia/nodes_models.py
ubicquia/public_safety.py
ubicquia/reports.py
ubicquia/setup_logger.py
ubicquia/shortcuts.py
ubicquia/traffic_mobility.py
ubicquia/traffic_mobility_models.py
ubicquia/utils.py
ubicquia/wifi.py
ubicquia/wifi_captive_portal.py
ubicquia-0.8.5.dist-info/LICENSE.txt
ubicquia-0.8.5.dist-info/METADATA
ubicquia-0.8.5.dist-info/WHEEL
ubicquia-0.8.5.dist-info/top_level.txt
ubicquia-0.8.5.dist-info/RECORD
