Metadata-Version: 2.1
Name: ubicquia
Version: 0.8.5
Summary: Ubicquia API Client Library
Author: CiberC Dev
License: GPLv3
License-File: LICENSE.txt
Requires-Dist: requests >=2.28
Requires-Dist: requests-oauthlib
Requires-Dist: pydantic >=1.9
